ps_scanner-1.0.0.data/scripts/ps-scanner
src/__init__.py
src/scanner.py
ps_scanner-1.0.0.dist-info/METADATA
ps_scanner-1.0.0.dist-info/WHEEL
ps_scanner-1.0.0.dist-info/top_level.txt
ps_scanner-1.0.0.dist-info/RECORD
